weverse/__init__.py
weverse/enums.py
weverse/errors.py
weverse/fetcher.py
weverse/url.py
weverse/utils.py
weverse/weverse.py
weverse/objects/__init__.py
weverse/objects/attachment.py
weverse/objects/comment.py
weverse/objects/community.py
weverse/objects/live.py
weverse/objects/media.py
weverse/objects/member.py
weverse/objects/moment.py
weverse/objects/notice.py
weverse/objects/notification.py
weverse/objects/post.py
Weverse.py-1.0.3.dist-info/LICENSE
Weverse.py-1.0.3.dist-info/METADATA
Weverse.py-1.0.3.dist-info/WHEEL
Weverse.py-1.0.3.dist-info/top_level.txt
Weverse.py-1.0.3.dist-info/RECORD
