Metadata-Version: 2.1
Name: Weverse.py
Version: 1.0.3
Summary: Weverse.py seeks to provide developers with a tool that allows them to make a bot that is able to retrieve Weverse Posts in semi real-time with relative ease.
Home-page: https://github.com/Anson-Quek/Weverse.py
Author: Anson Quek
License: MIT
Classifier: Development Status :: 5 - Production/Stable
Classifier: License :: OSI Approved :: MIT License
Classifier: Intended Audience :: Developers
Classifier: Natural Language :: English
Classifier: Programming Language :: Python :: 3.10
Requires-Python: >=3.10
License-File: LICENSE
Requires-Dist: aiohttp (==3.8.3)
Requires-Dist: setuptools
